MANIFEST.in
README.md
requirements.txt
setup.py
postgis/__init__.py
postgis/__meta__.py
postgis/geojson.py
postgis/geometry.py
postgis/geometrycollection.py
postgis/linestring.py
postgis/multi.py
postgis/multilinestring.py
postgis/multipoint.py
postgis/multipolygon.py
postgis/point.py
postgis/polygon.py
postgis/reader.py
psycopg_postgis2.egg-info/PKG-INFO
psycopg_postgis2.egg-info/SOURCES.txt
psycopg_postgis2.egg-info/dependency_links.txt
psycopg_postgis2.egg-info/requires.txt
psycopg_postgis2.egg-info/top_level.txt