Metadata-Version: 1.1
Name: psycopg-postgis2
Version: 0.0.1
Summary: Pyscopg helpers to work with PostGIS.
Home-page: https://github.com/bitwolaiye/psycopg-postgis
Author: Yohan Boniface, Zhou Qi
Author-email: yohan.boniface@data.gouv.fr, bitwolaiye@gmail.com
License: WTFPL
Keywords: psycopg postgis gis python2
Platform: UNKNOWN
Classifier: Development Status :: 4 - Beta
Classifier: Intended Audience :: Developers
Classifier: Topic :: Scientific/Engineering :: GIS
Classifier: Programming Language :: Python :: 2
Classifier: Programming Language :: Python :: 2.7
